MANIFEST.in
README.md
setup.py
FEW.egg-info/PKG-INFO
FEW.egg-info/SOURCES.txt
FEW.egg-info/dependency_links.txt
FEW.egg-info/entry_points.txt
FEW.egg-info/requires.txt
FEW.egg-info/top_level.txt
FEW.egg-info/zip-safe
few/__init__.py
few/_version.py
few/evaluation.py
few/few.py
few/population.py
few/selection.py
few/variation.py
few/lib/epsilon_lexicase.h
few/lib/evaluation.h
few/lib/few_lib.cpp
few/lib/few_lib.pyx
few/tests/__init__.py
few/tests/test_evaluation.py
few/tests/test_few.py
few/tests/test_population.py
few/tests/test_selection.py
few/tests/test_variation.py